<?xml version="1.0"?>
<!--
/**
 * Dhl Shipping
 *
 * NOTICE OF LICENSE
 *
 * This source file is subject to the Open Software License (OSL 3.0)
 * that is bundled with this package in the file LICENSE.txt.
 * It is also available through the world-wide-web at this URL:
 * http://opensource.org/licenses/osl-3.0.php
 *
 * DISCLAIMER
 *
 * Do not edit or add to this file if you wish to upgrade this extension to
 * newer versions in the future.
 *
 * @category  Dhl
 * @package   Dhl\Shipping
 * @author    Benjamin Heuer <benjamin.heuer@netresearch.de>
 * @copyright 2017 Netresearch GmbH & Co. KG
 * @license   http://opensource.org/licenses/osl-3.0.php Open Software License (OSL 3.0)
 * @link      http://www.netresearch.de/
 */
-->
<config xmlns:xsi="http://www.w3.org/2001/XMLSchema-instance"
        xsi:noNamespaceSchemaLocation="urn:magento:framework:Event/etc/events.xsd">
    <event name="payment_method_is_active">
        <observer name="shipping_disable_cod_payment" instance="Dhl\Shipping\Observer\DisableCodPaymentObserver"/>
    </event>
    <event name="sales_order_place_after">
        <observer name="shipping_update_carrier" instance="Dhl\Shipping\Observer\UpdateCarrierObserver" />
    </event>
    <event name="sales_model_service_quote_submit_success">
        <observer name="shipping_persist_info_to_address" instance="Dhl\Shipping\Observer\ShiftShippingInfoObserver" />
    </event>
    <event name="adminhtml_block_html_before">
        <observer name="shipping_extend_address_form" instance="Dhl\Shipping\Observer\ExtendAddressFormObserver" />
    </event>
    <event name="admin_sales_order_address_update">
        <observer name="shipping_update_shipping_info" instance="Dhl\Shipping\Observer\UpdateShippingInfoObserver" />
    </event>
    <event name="sales_order_shipment_track_delete_before">
        <observer name="shipping_delete_track" instance="Dhl\Shipping\Observer\DeleteTrackObserver" />
    </event>
    <event name="checkout_submit_all_after">
        <observer name="shipping_init_label_status" instance="Dhl\Shipping\Observer\UpdateLabelStatusObserver" />
    </event>
    <event name="dhlshipping_label_create_after">
        <observer name="shipping_update_label_status" instance="Dhl\Shipping\Observer\UpdateLabelStatusObserver" />
    </event>
</config>
